{"cameraMode":{"drawMode":0,"name":"Shaded","section":"Shading Mode"},"sceneLighting":true,"audioPlay":false,"sceneViewState":{"m_AlwaysRefresh":false,"showFog":true,"showSkybox":true,"showFlares":true,"showImageEffects":true,"showParticleSystems":true,"showVisualEffectGraphs":true,"m_FxEnabled":true},"in2DMode":false,"pivot":{"x":8.756380081176758,"y":5.672426223754883,"z":-11.688216209411621},"rotation":{"x":-0.06783488392829895,"y":-0.720780074596405,"z":0.07191680371761322,"w":-0.6864289045333862},"size":54.573585510253909,"orthographic":false}