{"cameraMode":{"drawMode":0,"name":"Shaded","section":"Shading Mode"},"sceneLighting":true,"audioPlay":false,"sceneViewState":{"m_AlwaysRefresh":true,"showFog":true,"showSkybox":true,"showFlares":true,"showImageEffects":true,"showParticleSystems":true,"showVisualEffectGraphs":true,"m_FxEnabled":true},"in2DMode":false,"pivot":{"x":-5.61032247543335,"y":8.079355239868164,"z":-8.692339897155762},"rotation":{"x":-0.06361868977546692,"y":-0.7062638998031616,"z":0.06271865218877793,"w":-0.703102171421051},"size":10.589225769042969,"orthographic":false}